{"updated_at":"2026-07-11T02:30:37.729Z","total_packages":94,"packages":[{"key":"694869ca23fa9832","file":"case_library/packages/694869ca23fa9832.json","cat":"平板","level1":"屏幕显示","level2":"压伤","level3_new":"明显","count":1,"updated_at":"2026-07-06T02:05:00.537Z"},{"key":"8311242b3958a6b5","file":"case_library/packages/8311242b3958a6b5.json","cat":"平板","level1":"屏幕显示","level2":"色斑","level3_new":"明显","count":1,"updated_at":"2026-07-05T01:57:27.364Z"},{"key":"0d373b6b67ce3345","file":"case_library/packages/0d373b6b67ce3345.json","cat":"平板","level1":"拆修及浸液情况","level2":"屏幕拆修","level3_new":"屏幕-黑边不齐","count":2,"updated_at":"2026-07-11T02:30:37.729Z"},{"key":"b3ebc88499800866","file":"case_library/packages/b3ebc88499800866.json","cat":"平板","level1":"维修浸液","level2":"屏幕维修","level3_new":"更换屏幕外玻璃","count":5,"updated_at":"2026-07-09T02:28:52.496Z"},{"key":"2c8008b1380b792a","file":"case_library/packages/2c8008b1380b792a.json","cat":"平板","level1":"维修浸液","level2":"摄像头","level3_new":"后摄更换","count":1,"updated_at":"2026-07-08T02:44:44.415Z"},{"key":"b4e6d560d39a96ba","file":"case_library/packages/b4e6d560d39a96ba.json","cat":"平板","level1":"维修浸液","level2":"组件","level3_new":"后摄镜片更换","count":1,"updated_at":"2026-07-08T02:44:44.415Z"},{"key":"ac34bf5cd2cf576d","file":"case_library/packages/ac34bf5cd2cf576d.json","cat":"手机","level1":"","level2":"","level3_new":"IMEI-录错","count":1,"updated_at":"2026-07-11T02:30:37.729Z"},{"key":"6786eb1e0b462c8a","file":"case_library/packages/6786eb1e0b462c8a.json","cat":"手机","level1":"","level2":"","level3_new":"基础问题-未撕膜","count":1,"updated_at":"2026-07-11T02:30:37.729Z"},{"key":"75316578a9c41679","file":"case_library/packages/75316578a9c41679.json","cat":"手机","level1":"","level2":"","level3_new":"基础问题-未还原","count":1,"updated_at":"2026-07-05T01:57:27.364Z"},{"key":"fe2728ab2ea12ada","file":"case_library/packages/fe2728ab2ea12ada.json","cat":"手机","level1":"","level2":"","level3_new":"基础问题-防拆标不规范","count":1,"updated_at":"2026-07-05T01:57:27.364Z"},{"key":"6ce6ad3c908ccee0","file":"case_library/packages/6ce6ad3c908ccee0.json","cat":"手机","level1":"","level2":"","level3_new":"基础问题—来源不符","count":1,"updated_at":"2026-07-09T02:28:52.496Z"},{"key":"96e23519a306f180","file":"case_library/packages/96e23519a306f180.json","cat":"手机","level1":"","level2":"","level3_new":"拆机-未复原到位","count":3,"updated_at":"2026-07-09T02:28:52.496Z"},{"key":"17341713045feaa5","file":"case_library/packages/17341713045feaa5.json","cat":"手机","level1":"","level2":"","level3_new":"网络制式-录错","count":1,"updated_at":"2026-07-08T02:44:44.415Z"},{"key":"1fc4b4ee9abc0915","file":"case_library/packages/1fc4b4ee9abc0915.json","cat":"手机","level1":"","level2":"","level3_new":"颜色录错","count":1,"updated_at":"2026-07-08T02:44:44.415Z"},{"key":"eca91a951e43471c","file":"case_library/packages/eca91a951e43471c.json","cat":"手机","level1":"主屏外观","level2":"贴膜情况","level3_new":"无保护膜","count":1,"updated_at":"2026-07-06T02:05:00.536Z"},{"key":"d7b4f1d8363deea8","file":"case_library/packages/d7b4f1d8363deea8.json","cat":"手机","level1":"充电","level2":"有线充电","level3_new":"异常","count":1,"updated_at":"2026-07-08T02:44:44.414Z"},{"key":"bd4946b3b36a0fce","file":"case_library/packages/bd4946b3b36a0fce.json","cat":"手机","level1":"充电","level2":"有线充电","level3_new":"接触不良","count":1,"updated_at":"2026-07-04T23:12:51.262Z"},{"key":"38e6c528535766c1","file":"case_library/packages/38e6c528535766c1.json","cat":"手机","level1":"其它状况","level2":"屏幕切换/悬停","level3_new":"异常","count":1,"updated_at":"2026-07-05T01:57:27.364Z"},{"key":"3b55ffc5f6ce89bf","file":"case_library/packages/3b55ffc5f6ce89bf.json","cat":"手机","level1":"副屏屏幕外观","level2":"屏幕/其它","level3_new":"屏幕边缘脱胶","count":2,"updated_at":"2026-07-08T02:44:44.414Z"},{"key":"a6ee30c86a9b58e9","file":"case_library/packages/a6ee30c86a9b58e9.json","cat":"手机","level1":"副屏屏幕显示","level2":"色斑","level3_new":"直径＞5mm","count":1,"updated_at":"2026-07-05T01:57:27.364Z"},{"key":"938fc3b13e05ddea","file":"case_library/packages/938fc3b13e05ddea.json","cat":"手机","level1":"声音与振动","level2":"振动","level3_new":"异常","count":1,"updated_at":"2026-07-04T23:12:51.263Z"},{"key":"66fb1fe6f80fb198","file":"case_library/packages/66fb1fe6f80fb198.json","cat":"手机","level1":"外壳外观","level2":"卡托","level3_new":"更换","count":3,"updated_at":"2026-07-11T02:30:37.729Z"},{"key":"f1eec4cf3e898d75","file":"case_library/packages/f1eec4cf3e898d75.json","cat":"手机","level1":"外壳外观","level2":"碎裂","level3_new":"2mm-10mm","count":8,"updated_at":"2026-07-11T02:30:37.729Z"},{"key":"0f5a011e60c9d2af","file":"case_library/packages/0f5a011e60c9d2af.json","cat":"手机","level1":"外壳外观","level2":"脱胶/缝隙","level3_new":"脱胶缝隙 ≥0.3mm","count":3,"updated_at":"2026-07-11T02:30:37.729Z"},{"key":"ba79f5e68b618f01","file":"case_library/packages/ba79f5e68b618f01.json","cat":"手机","level1":"屏幕外观","level2":"屏幕/其它","level3_new":"屏幕边缘脱胶","count":6,"updated_at":"2026-07-09T02:28:52.496Z"},{"key":"7786bbde0bf7a09d","file":"case_library/packages/7786bbde0bf7a09d.json","cat":"手机","level1":"屏幕外观","level2":"碎裂/脱胶","level3_new":"屏幕边缘脱胶","count":5,"updated_at":"2026-07-08T02:44:44.415Z"},{"key":"5f7eb23d332ece28","file":"case_library/packages/5f7eb23d332ece28.json","cat":"手机","level1":"屏幕外观","level2":"碎裂","level3_new":">5mm或数量>1","count":2,"updated_at":"2026-07-08T02:44:44.414Z"},{"key":"c4376567a7901180","file":"case_library/packages/c4376567a7901180.json","cat":"手机","level1":"屏幕外观","level2":"碎裂","level3_new":"1.5mm-5mm且数量=1","count":2,"updated_at":"2026-07-09T02:28:52.496Z"},{"key":"86d2cafc916badb3","file":"case_library/packages/86d2cafc916badb3.json","cat":"手机","level1":"屏幕显示","level2":"亮点/亮斑","level3_new":"直径＞5且数量≥1","count":1,"updated_at":"2026-07-08T02:44:44.415Z"},{"key":"fd63dd698c758597","file":"case_library/packages/fd63dd698c758597.json","cat":"手机","level1":"屏幕显示","level2":"其它","level3_new":"压伤","count":3,"updated_at":"2026-07-08T02:44:44.414Z"},{"key":"e5c3ae666c4cf8bc","file":"case_library/packages/e5c3ae666c4cf8bc.json","cat":"手机","level1":"屏幕显示","level2":"其它","level3_new":"条纹/花屏/闪屏","count":3,"updated_at":"2026-07-08T02:44:44.415Z"},{"key":"a9487acfb3808727","file":"case_library/packages/a9487acfb3808727.json","cat":"手机","level1":"屏幕显示","level2":"其它","level3_new":"漏液（坏点＞0.5mm）","count":2,"updated_at":"2026-07-08T02:44:44.414Z"},{"key":"b8a05b07fe82d60f","file":"case_library/packages/b8a05b07fe82d60f.json","cat":"手机","level1":"屏幕显示","level2":"图文残影","level3_new":"状态栏以外透图（可拍）","count":1,"updated_at":"2026-07-04T23:12:51.263Z"},{"key":"3a29e0547a3ff637","file":"case_library/packages/3a29e0547a3ff637.json","cat":"手机","level1":"屏幕显示","level2":"图文残影","level3_new":"状态栏以外透图直径＞30mm或数量＞10","count":2,"updated_at":"2026-07-05T01:57:27.364Z"},{"key":"4b1d4e349c0ebd81","file":"case_library/packages/4b1d4e349c0ebd81.json","cat":"手机","level1":"屏幕显示","level2":"坏点","level3_new":"直径 ≤0.5mm且数量＞6","count":2,"updated_at":"2026-07-08T02:44:44.415Z"},{"key":"d90a712fbb127b58","file":"case_library/packages/d90a712fbb127b58.json","cat":"手机","level1":"屏幕显示","level2":"显示情况","level3_new":"显示异常/无法正常显示","count":10,"updated_at":"2026-07-11T02:30:37.729Z"},{"key":"db6a2e555774aead","file":"case_library/packages/db6a2e555774aead.json","cat":"手机","level1":"屏幕显示","level2":"显示情况","level3_new":"泛红/泛黄：明显（可拍）","count":1,"updated_at":"2026-07-05T01:57:27.364Z"},{"key":"32d8f57c7f43d291","file":"case_library/packages/32d8f57c7f43d291.json","cat":"手机","level1":"屏幕显示","level2":"显示情况","level3_new":"状态栏以外透图（可拍）","count":1,"updated_at":"2026-07-08T02:44:44.414Z"},{"key":"9c6be407639f213f","file":"case_library/packages/9c6be407639f213f.json","cat":"手机","level1":"屏幕显示","level2":"气泡","level3_new":"直径＞1mm或数量＞3","count":1,"updated_at":"2026-07-04T23:12:51.263Z"},{"key":"ace0823322f342a5","file":"case_library/packages/ace0823322f342a5.json","cat":"手机","level1":"屏幕显示","level2":"色斑","level3_new":"直径＞5mm","count":3,"updated_at":"2026-07-08T02:44:44.414Z"},{"key":"ebfebd2c69f6f5c3","file":"case_library/packages/ebfebd2c69f6f5c3.json","cat":"手机","level1":"屏幕显示","level2":"进灰","level3_new":"直径≤0.5mm且数量4-10；直径＞0.5mm且数量1-5","count":2,"updated_at":"2026-07-11T02:30:37.729Z"},{"key":"19a5e14abf582162","file":"case_library/packages/19a5e14abf582162.json","cat":"手机","level1":"按键","level2":"其它按键","level3_new":"失灵","count":2,"updated_at":"2026-07-06T02:05:00.536Z"},{"key":"81b9c3629cf312dd","file":"case_library/packages/81b9c3629cf312dd.json","cat":"手机","level1":"摄像头","level2":"前置摄像头","level3_new":"坏点数量＞15或直径＞5mm","count":1,"updated_at":"2026-07-08T02:44:44.415Z"},{"key":"81ace1324a4ed779","file":"case_library/packages/81ace1324a4ed779.json","cat":"手机","level1":"摄像头","level2":"前置摄像头","level3_new":"坏点数量＞1或直径＞0.5mm","count":10,"updated_at":"2026-07-09T02:28:52.496Z"},{"key":"b2fba1400d791f29","file":"case_library/packages/b2fba1400d791f29.json","cat":"手机","level1":"摄像头","level2":"前置摄像头","level3_new":"有斑数量≤15且直径≤20mm","count":1,"updated_at":"2026-07-11T02:30:37.729Z"},{"key":"5a71c9891f7b6260","file":"case_library/packages/5a71c9891f7b6260.json","cat":"手机","level1":"摄像头","level2":"前置摄像头","level3_new":"有斑数量≤3且直径≤5mm","count":5,"updated_at":"2026-07-11T02:30:37.729Z"},{"key":"443f5c9969a78023","file":"case_library/packages/443f5c9969a78023.json","cat":"手机","level1":"摄像头","level2":"前置摄像头","level3_new":"画面异常","count":1,"updated_at":"2026-07-04T23:12:51.263Z"},{"key":"ea0ce6c1e64c6af5","file":"case_library/packages/ea0ce6c1e64c6af5.json","cat":"手机","level1":"摄像头","level2":"后置摄像头","level3_new":"后摄白底拍照有斑","count":1,"updated_at":"2026-07-08T02:44:44.415Z"},{"key":"36a9f03a6ac850b5","file":"case_library/packages/36a9f03a6ac850b5.json","cat":"手机","level1":"摄像头","level2":"后置摄像头","level3_new":"坏点数量＞1或直径＞0.5mm","count":4,"updated_at":"2026-07-11T02:30:37.729Z"},{"key":"f0bb64b4275c17e5","file":"case_library/packages/f0bb64b4275c17e5.json","cat":"手机","level1":"摄像头","level2":"后置摄像头","level3_new":"有斑数量≤15且直径≤20mm","count":9,"updated_at":"2026-07-11T02:30:37.729Z"},{"key":"b5ecb037e65da05c","file":"case_library/packages/b5ecb037e65da05c.json","cat":"手机","level1":"摄像头","level2":"后置摄像头","level3_new":"有斑数量≤3且直径≤5mm","count":33,"updated_at":"2026-07-11T02:30:37.729Z"},{"key":"48c9dc64993d7a1b","file":"case_library/packages/48c9dc64993d7a1b.json","cat":"手机","level1":"摄像头","level2":"后置摄像头","level3_new":"画面异常","count":2,"updated_at":"2026-07-08T02:44:44.414Z"},{"key":"534639dcead32291","file":"case_library/packages/534639dcead32291.json","cat":"手机","level1":"摄像头","level2":"摄像头功能","level3_new":"前摄/后摄画面异常","count":4,"updated_at":"2026-07-11T02:30:37.729Z"},{"key":"aa87a0c88cde794b","file":"case_library/packages/aa87a0c88cde794b.json","cat":"手机","level1":"摄像头","level2":"摄像头功能","level3_new":"前摄拍照有坏点","count":4,"updated_at":"2026-07-08T02:44:44.415Z"},{"key":"506d27ac1556e7e1","file":"case_library/packages/506d27ac1556e7e1.json","cat":"手机","level1":"摄像头","level2":"摄像头功能","level3_new":"后摄拍照有坏点","count":4,"updated_at":"2026-07-09T02:28:52.496Z"},{"key":"eb3cf3d20347e503","file":"case_library/packages/eb3cf3d20347e503.json","cat":"手机","level1":"摄像头","level2":"摄像头功能","level3_new":"摄像头/闪光灯/升降摄像头-无法打开","count":1,"updated_at":"2026-07-08T02:44:44.414Z"},{"key":"5f5914a668c4d9e6","file":"case_library/packages/5f5914a668c4d9e6.json","cat":"手机","level1":"维修浸液","level2":"屏幕","level3_new":"外屏-APP黑边红线有缺失","count":1,"updated_at":"2026-07-04T23:12:51.262Z"},{"key":"da0c0d29851b52af","file":"case_library/packages/da0c0d29851b52af.json","cat":"手机","level1":"维修浸液","level2":"屏幕","level3_new":"外屏-有胶水溢出","count":2,"updated_at":"2026-07-11T02:30:37.729Z"},{"key":"1bdb714de4e048fb","file":"case_library/packages/1bdb714de4e048fb.json","cat":"手机","level1":"维修浸液","level2":"屏幕","level3_new":"外屏-有胶水溢出/撬痕","count":5,"updated_at":"2026-07-06T02:05:00.536Z"},{"key":"8b72d1c31ff01b54","file":"case_library/packages/8b72d1c31ff01b54.json","cat":"手机","level1":"维修浸液","level2":"屏幕","level3_new":"外屏-紫光灯照射边缘内屏异常","count":1,"updated_at":"2026-07-06T02:05:00.536Z"},{"key":"d5a79662e2eb6e31","file":"case_library/packages/d5a79662e2eb6e31.json","cat":"手机","level1":"维修浸液","level2":"屏幕","level3_new":"屏幕-关于本机提示未知部件/无法验证","count":1,"updated_at":"2026-07-08T02:44:44.415Z"},{"key":"e1439ee72a509269","file":"case_library/packages/e1439ee72a509269.json","cat":"手机","level1":"维修浸液","level2":"屏幕","level3_new":"屏幕支架更换","count":1,"updated_at":"2026-07-09T02:28:52.496Z"},{"key":"08c3c4ee353bbbc2","file":"case_library/packages/08c3c4ee353bbbc2.json","cat":"手机","level1":"维修浸液","level2":"屏幕","level3_new":"工具-屏幕偏光检测异常","count":2,"updated_at":"2026-07-09T02:28:52.496Z"},{"key":"fff5bed2145e6401","file":"case_library/packages/fff5bed2145e6401.json","cat":"手机","level1":"维修浸液","level2":"机身","level3_new":"后壳-与中框有溢胶/撬痕","count":15,"updated_at":"2026-07-11T02:30:37.729Z"},{"key":"1f2c977d3b09d18e","file":"case_library/packages/1f2c977d3b09d18e.json","cat":"手机","level1":"维修浸液","level2":"机身","level3_new":"后壳-后盖与摄像头存在缝隙","count":1,"updated_at":"2026-07-04T23:12:51.262Z"},{"key":"ce48699ef42f038d","file":"case_library/packages/ce48699ef42f038d.json","cat":"手机","level1":"维修浸液","level2":"机身","level3_new":"后壳-后盖与镜头保护罩连接处有胶水溢出","count":6,"updated_at":"2026-07-11T02:30:37.729Z"},{"key":"fb7306ab54bc441b","file":"case_library/packages/fb7306ab54bc441b.json","cat":"手机","level1":"维修浸液","level2":"机身","level3_new":"后壳-壳内漆面受损","count":10,"updated_at":"2026-07-09T02:28:52.496Z"},{"key":"b7bb52485c21f1c5","file":"case_library/packages/b7bb52485c21f1c5.json","cat":"手机","level1":"维修浸液","level2":"机身","level3_new":"后壳-扬声器网/麦克风网缺失","count":2,"updated_at":"2026-07-05T01:57:27.364Z"},{"key":"41e0b2b691130afa","file":"case_library/packages/41e0b2b691130afa.json","cat":"手机","level1":"维修浸液","level2":"机身","level3_new":"后壳-样式不匹配","count":5,"updated_at":"2026-07-09T02:28:52.496Z"},{"key":"3f06bfce1d332a5b","file":"case_library/packages/3f06bfce1d332a5b.json","cat":"手机","level1":"维修浸液","level2":"机身","level3_new":"外壳开孔切割弧度与原装不符","count":2,"updated_at":"2026-07-06T02:05:00.536Z"},{"key":"13a409548149aa3b","file":"case_library/packages/13a409548149aa3b.json","cat":"手机","level1":"维修浸液","level2":"电池","level3_new":"电池健康值不符","count":2,"updated_at":"2026-07-05T01:57:27.364Z"},{"key":"bd16663bf94e34b8","file":"case_library/packages/bd16663bf94e34b8.json","cat":"手机","level1":"维修浸液","level2":"电池","level3_new":"电池提示异常情况/故障","count":1,"updated_at":"2026-07-08T02:44:44.415Z"},{"key":"56e6d1f686df02fe","file":"case_library/packages/56e6d1f686df02fe.json","cat":"手机","level1":"维修浸液","level2":"零件维修/更换","level3_new":"激光雷达维修/更换","count":1,"updated_at":"2026-07-08T02:44:44.415Z"},{"key":"7c0dda414ed1e8d3","file":"case_library/packages/7c0dda414ed1e8d3.json","cat":"手机","level1":"维修浸液","level2":"零件维修/更换","level3_new":"部分零件维修更换","count":3,"updated_at":"2026-07-04T23:12:51.262Z"},{"key":"2cd58c4282c7b8d1","file":"case_library/packages/2cd58c4282c7b8d1.json","cat":"手表","level1":"","level2":"","level3_new":"版本-录错","count":1,"updated_at":"2026-07-05T01:57:27.364Z"},{"key":"abacf5f9d1ac63f8","file":"case_library/packages/abacf5f9d1ac63f8.json","cat":"手表","level1":"充电功能","level2":"充电器功能","level3_new":"正常","count":1,"updated_at":"2026-07-09T02:28:52.496Z"},{"key":"6b1ce33ff9da182c","file":"case_library/packages/6b1ce33ff9da182c.json","cat":"手表","level1":"其它状况","level2":"其它状况","level3_new":"公交卡/门禁卡无法解除","count":1,"updated_at":"2026-07-11T02:30:37.729Z"},{"key":"2050afd6fb4d74ed","file":"case_library/packages/2050afd6fb4d74ed.json","cat":"手表","level1":"其它状况","level2":"其它状况","level3_new":"无法连接/配对","count":1,"updated_at":"2026-07-05T01:57:27.364Z"},{"key":"282e454b23e181d9","file":"case_library/packages/282e454b23e181d9.json","cat":"手表","level1":"功能情况*","level2":"拍照功能","level3_new":"拍照(无法打开/无法对焦/成像异常)","count":1,"updated_at":"2026-07-09T02:28:52.496Z"},{"key":"1c8e86bf3ebe6002","file":"case_library/packages/1c8e86bf3ebe6002.json","cat":"手表","level1":"机身外观","level2":"表带使用情况","level3_new":"更换第三方表带","count":1,"updated_at":"2026-07-04T23:12:51.263Z"},{"key":"e4bab5df773f129a","file":"case_library/packages/e4bab5df773f129a.json","cat":"手表","level1":"维修浸液","level2":"维修浸液","level3_new":"零件维修/更换","count":1,"updated_at":"2026-07-05T01:57:27.364Z"},{"key":"6530b9b5bb27a3ce","file":"case_library/packages/6530b9b5bb27a3ce.json","cat":"笔记本","level1":"C面/外置键盘外观*","level2":"键盘外观","level3_new":"定制键盘语言/布局","count":1,"updated_at":"2026-07-08T02:44:44.415Z"},{"key":"5df3f8aa0dfbae02","file":"case_library/packages/5df3f8aa0dfbae02.json","cat":"笔记本","level1":"其他外观*","level2":"其他外观","level3_new":"接口外观异常","count":1,"updated_at":"2026-07-11T02:30:37.729Z"},{"key":"8ff346ad94bfd6a0","file":"case_library/packages/8ff346ad94bfd6a0.json","cat":"笔记本","level1":"功能情况*","level2":"USB接口功能","level3_new":"USB/Type-C接口功能异常(失灵/变形导致无法使用)","count":1,"updated_at":"2026-07-08T02:44:44.415Z"},{"key":"ab97d706051b159d","file":"case_library/packages/ab97d706051b159d.json","cat":"笔记本","level1":"功能情况*","level2":"充电器情况","level3_new":"充电器异常/缺失(不匹配/异响/损坏)","count":1,"updated_at":"2026-07-04T23:12:51.263Z"},{"key":"c7873950e2e70e5f","file":"case_library/packages/c7873950e2e70e5f.json","cat":"笔记本","level1":"功能情况*","level2":"其他功能","level3_new":"充电功能异常","count":1,"updated_at":"2026-07-08T02:44:44.415Z"},{"key":"3bc87e25d097596e","file":"case_library/packages/3bc87e25d097596e.json","cat":"笔记本","level1":"功能情况*","level2":"其他功能","level3_new":"电池情况异常","count":1,"updated_at":"2026-07-08T02:44:44.415Z"},{"key":"786b5bdc52eaa1e5","file":"case_library/packages/786b5bdc52eaa1e5.json","cat":"笔记本","level1":"功能情况*","level2":"声音功能","level3_new":"麦克风异常(无法录音)","count":1,"updated_at":"2026-07-09T02:28:52.496Z"},{"key":"211748f7f5f7b730","file":"case_library/packages/211748f7f5f7b730.json","cat":"笔记本","level1":"功能情况*","level2":"指纹功能","level3_new":"指纹功能正常","count":1,"updated_at":"2026-07-04T23:12:51.263Z"},{"key":"04cf037bba95d6a1","file":"case_library/packages/04cf037bba95d6a1.json","cat":"笔记本","level1":"拆修及浸液情况*","level2":"电池拆修情况","level3_new":"更换电池","count":1,"updated_at":"2026-07-08T02:44:44.415Z"},{"key":"3743ce58039b6364","file":"case_library/packages/3743ce58039b6364.json","cat":"笔记本","level1":"拆修及浸液情况*","level2":"螺丝情况","level3_new":"内部螺丝缺失","count":1,"updated_at":"2026-07-11T02:30:37.729Z"},{"key":"60e3422b2f282bf8","file":"case_library/packages/60e3422b2f282bf8.json","cat":"笔记本","level1":"维修浸液","level2":"部件更换","level3_new":"更换非原装电池","count":1,"updated_at":"2026-07-11T02:30:37.729Z"},{"key":"92daccae73013158","file":"case_library/packages/92daccae73013158.json","cat":"笔记本","level1":"购买渠道","level2":"","level3_new":"其他版本","count":2,"updated_at":"2026-07-09T02:28:52.496Z"},{"key":"00e973900f8bb2a4","file":"case_library/packages/00e973900f8bb2a4.json","cat":"耳机","level1":"充电盒外观","level2":"其他","level3_new":"充电盒刻字/图","count":1,"updated_at":"2026-07-08T02:44:44.415Z"}]}