{"1001869488|转转-成都智能验机中心|屏幕拆修情况|屏幕无以上问题|屏幕-显示边界异常":{"images":[],"note":""},"1001580424|转转-成都智能验机中心|机身||后壳-壳内漆面受损":{"images":[],"note":"质检太快"},"1001103852|转转-深圳智能验机中心|设备来源|零售机|官翻机":{"images":["https://zb-images-1423465873.cos.ap-guangzhou.myqcloud.com/qc-images/1001103852_转转-深圳智能验机中心_设备来源_零售机_官翻机_1779713151920.png"],"note":"111"},"1001093503|转转-深圳智能验机中心|电池拆修情况|电池无以上问题|电池-第三方标识/其他品牌/样式不符":{"images":["https://zb-images-1423465873.cos.ap-guangzhou.myqcloud.com/qc-images/1001093503_转转-深圳智能验机中心_电池拆修情况_电池无以上问题_电池-第三方标识_其他品牌_样式不符_1779713280142.png"],"note":""},"1001093503|转转-深圳智能验机中心|机身其他现象|—|卡托颜色或串号不符":{"images":["https://zb-images-1423465873.cos.ap-guangzhou.myqcloud.com/qc-images/1001093503_转转-深圳智能验机中心_机身其他现象_—_卡托颜色或串号不符_1779733107606.png"],"note":""},"1004289662|深圳后验中心仓|色斑|无|直径＞5mm":{"images":["https://zb-images-1423465873.cos.ap-guangzhou.myqcloud.com/qc-images/1004289662_深圳后验中心仓_色斑_无_直径＞5mm_1779760701026.png"],"note":"廖冬香"},"1001463755|转转-深圳智能验机中心|闪光灯功能|闪光灯功能正常|闪光灯/手电筒无法打开/灯光非白(黄)色":{"images":["https://zb-images-1423465873.cos.ap-guangzhou.myqcloud.com/qc-images/1001463755_转转-深圳智能验机中心_闪光灯功能_闪光灯功能正常_闪光灯_手电筒无法打开_灯光非白(黄)色_1779786787865.png"],"note":""},"1001093503|转转-深圳智能验机中心|机身其他现象||卡托颜色或串号不符":{"images":[],"note":"标准不清晰"},"1003959562|西安库|图文残影|无|状态栏以外透图（可拍）":{"images":["https://zb-images-1423465873.cos.ap-guangzhou.myqcloud.com/qc-images/1003959562_西安库_图文残影_无_状态栏以外透图（可拍）_1779790975524.png"],"note":""},"1003165574|西安库|碎裂|无|2mm-10mm":{"images":["https://zb-images-1423465873.cos.ap-guangzhou.myqcloud.com/qc-images/1003165574_西安库_碎裂_无_2mm-10mm_1779791293730.png"],"note":""},"1003165574|西安库|机身|—|后壳-壳内漆面受损":{"images":["https://zb-images-1423465873.cos.ap-guangzhou.myqcloud.com/qc-images/1003165574_西安库_机身_—_后壳-壳内漆面受损_1779791319946.png"],"note":""},"1001430561|西安库|后置摄像头||拍照坏点":{"images":[],"note":"新人问题，没有看到这个问题"},"1004634801|转转-成都智能验机中心|工具读出维修|屏幕-工具读出异常|屏幕-工具读出异常":{"images":[],"note":"朱彪，工艺推送信息未更新至标准。"},"1003959626|转转-成都智能验机中心|前置摄像头||拍照坏点":{"images":[],"note":"坏点不很明显，不容易看到"},"1003959626|转转-成都智能验机中心|后置摄像头||拍照坏点":{"images":[],"note":"坏点不是很明显"},"999390518|青岛后验中心仓|碎裂|无|2mm-10mm":{"images":["https://zb-images-1423465873.cos.ap-guangzhou.myqcloud.com/qc-images/999390518_青岛后验中心仓_碎裂_无_2mm-10mm_1779876089114.png"],"note":"原质检师毕明洋"},"1003541652|青岛后验中心仓|电池|—|更换第三方电池":{"images":["https://zb-images-1423465873.cos.ap-guangzhou.myqcloud.com/qc-images/1003541652_青岛后验中心仓_电池_—_更换第三方电池_1779880973873.png"],"note":""},"1004480530|深圳后验中心仓|机身|—|后壳-后盖与镜头保护罩连接处有胶水溢出":{"images":["https://zb-images-1423465873.cos.ap-guangzhou.myqcloud.com/qc-images/1004480530_深圳后验中心仓_机身_—_后壳-后盖与镜头保护罩连接处有胶水溢出_1779979984557.png"],"note":""},"1004805827|转转-深圳智能验机中心|机身其他现象|—|卡托颜色或串号不符":{"images":["https://zb-images-1423465873.cos.ap-guangzhou.myqcloud.com/qc-images/1004805827_转转-深圳智能验机中心_机身其他现象_—_卡托颜色或串号不符_1780033373055.png"],"note":""},"1004805827|转转-深圳智能验机中心|机身其他现象||卡托颜色或串号不符":{"images":[],"note":"张开勇"},"1000935610|深圳后验中心仓|摄像头功能|前摄/后摄画面异常|前摄/后摄画面异常":{"images":["https://zb-images-1423465873.cos.ap-guangzhou.myqcloud.com/qc-images/1000935610_深圳后验中心仓_摄像头功能_前摄_后摄画面异常_前摄_后摄画面异常_1780065790482.png"],"note":""},"1001106888|深圳后验中心仓|碎裂/脱胶|—|屏幕边缘脱胶":{"images":["https://zb-images-1423465873.cos.ap-guangzhou.myqcloud.com/qc-images/1001106888_深圳后验中心仓_碎裂_脱胶_—_屏幕边缘脱胶_1780065825475.png"],"note":""},"997980084|转转-成都智能验机中心|图文残影|状态栏透图（可拍）|状态栏以外透图（不可拍）":{"images":[],"note":""},"1005498388|转转-深圳智能验机中心|—|全网通|移动全网通":{"images":["https://zb-images-1423465873.cos.ap-guangzhou.myqcloud.com/qc-images/1005498388_转转-深圳智能验机中心_—_全网通_移动全网通_1780285360700.png"],"note":""},"1003897225|转转-深圳智能验机中心|前置摄像头|—|拍照坏点":{"images":["https://zb-images-1423465873.cos.ap-guangzhou.myqcloud.com/qc-images/1003897225_转转-深圳智能验机中心_前置摄像头_—_拍照坏点_1780285404353.png"],"note":""},"1005731583|转转-深圳智能验机中心|显示情况|—|泛红/泛黄：明显（可拍）":{"images":["https://zb-images-1423465873.cos.ap-guangzhou.myqcloud.com/qc-images/1005731583_转转-深圳智能验机中心_显示情况_—_泛红_泛黄：明显（可拍）_1780285430651.png"],"note":""},"1005725858|转转-深圳智能验机中心|通话功能-SIM卡1|有网络锁，无法检测|卡1(不读卡/无信号/卡槽坏/无法拨号/基带坏)":{"images":["https://zb-images-1423465873.cos.ap-guangzhou.myqcloud.com/qc-images/1005725858_转转-深圳智能验机中心_通话功能-SIM卡1_有网络锁，无法检测_卡1(不读卡_无信号_卡槽坏_无法拨号_基带坏)_1780285451164.png"],"note":""},"1004480567|深圳后验中心仓|后置摄像头|—|画面异常":{"images":["https://zb-images-1423465873.cos.ap-guangzhou.myqcloud.com/qc-images/1004480567_深圳后验中心仓_后置摄像头_—_画面异常_1780285841168.png"],"note":""},"1005556649|深圳后验中心仓|后置摄像头|—|画面异常":{"images":["https://zb-images-1423465873.cos.ap-guangzhou.myqcloud.com/qc-images/1005556649_深圳后验中心仓_后置摄像头_—_画面异常_1780285880980.png"],"note":""},"1002395103|深圳后验中心仓|脱胶/缝隙|无（脱胶縫隙<0.3mm）|脱胶缝隙 ≥0.3mm":{"images":["https://zb-images-1423465873.cos.ap-guangzhou.myqcloud.com/qc-images/1002395103_深圳后验中心仓_脱胶_缝隙_无（脱胶縫隙_0.3mm）_脱胶缝隙 ≥0.3mm_1780370999095.png"],"note":""},"1002395103|深圳后验中心仓|进灰|无|直径≤0.5mm且数量4-10；直径＞0.5mm且数量1-5":{"images":["https://zb-images-1423465873.cos.ap-guangzhou.myqcloud.com/qc-images/1002395103_深圳后验中心仓_进灰_无_直径≤0.5mm且数量4-10；直径＞0.5mm且数量1-5_1780371012946.png"],"note":""},"1004854363|西安库|机身|—|后壳-后盖与镜头保护罩连接处有胶水溢出":{"images":["https://zb-images-1423465873.cos.ap-guangzhou.myqcloud.com/qc-images/1004854363_西安库_机身_—_后壳-后盖与镜头保护罩连接处有胶水溢出_1780372637485.png"],"note":""},"1003556996|西安库|—|—|基础问题-未撕膜":{"images":["https://zb-images-1423465873.cos.ap-guangzhou.myqcloud.com/qc-images/1003556996_西安库_—_—_基础问题-未撕膜_1780372692188.png","https://zb-images-1423465873.cos.ap-guangzhou.myqcloud.com/qc-images/1003556996_西安库_—_—_基础问题-未撕膜_1780372741154.png"],"note":""},"1003661545|转转-深圳智能验机中心|后置摄像头|—|画面异常":{"images":["https://zb-images-1423465873.cos.ap-guangzhou.myqcloud.com/qc-images/1003661545_转转-深圳智能验机中心_后置摄像头_—_画面异常_1780452559669.png"],"note":""},"1004358626|转转-深圳智能验机中心|通话功能-SIM卡2|卡2不支持|卡2功能正常":{"images":["https://zb-images-1423465873.cos.ap-guangzhou.myqcloud.com/qc-images/1004358626_转转-深圳智能验机中心_通话功能-SIM卡2_卡2不支持_卡2功能正常_1780452602798.png"],"note":""},"1004480679|深圳后验中心仓|机身|—|后壳-壳内漆面受损":{"images":["https://zb-images-1423465873.cos.ap-guangzhou.myqcloud.com/qc-images/1004480679_深圳后验中心仓_机身_—_后壳-壳内漆面受损_1780452651686.png"],"note":""},"1002488620|转转-深圳智能验机中心|工具读出维修||电池-工具读出异常":{"images":[],"note":"拆修组"},"1003147914|转转-深圳智能验机中心|屏幕拆修情况|屏幕-有第三方标识|屏幕无以上问题":{"images":[],"note":"拆修组"},"1005394585|转转-深圳智能验机中心|工具读出维修||电池-工具读出异常":{"images":[],"note":"拆修组"},"1005396930|转转-深圳智能验机中心|后壳拆修|后壳无以上问题|后壳-激光雷达颜色异常":{"images":[],"note":"拆修组"},"1004480530|深圳后验中心仓|机身||后壳-后盖与镜头保护罩连接处有胶水溢出":{"images":[],"note":"拆修组"},"1004931664|深圳后验中心仓|机身||后壳-壳内漆面受损":{"images":[],"note":"拆修组"},"1004931664|深圳后验中心仓|机身|—|后壳-壳内漆面受损":{"images":["https://zb-images-1423465873.cos.ap-guangzhou.myqcloud.com/qc-images/1004931664_深圳后验中心仓_机身_—_后壳-壳内漆面受损_1780468305208.png"],"note":""},"1003147914|转转-深圳智能验机中心|后壳拆修|后壳无以上问题|后壳-有第三方标识":{"images":["https://zb-images-1423465873.cos.ap-guangzhou.myqcloud.com/qc-images/1003147914_转转-深圳智能验机中心_后壳拆修_后壳无以上问题_后壳-有第三方标识_1780468598921.png"],"note":""},"1006259368|转转-深圳智能验机中心|机身|—|后壳-样式不匹配":{"images":["https://zb-images-1423465873.cos.ap-guangzhou.myqcloud.com/qc-images/1006259368_转转-深圳智能验机中心_机身_—_后壳-样式不匹配_1780559294575.png"],"note":""},"1003929100|深圳后验中心仓|图文残影|状态栏以外透图直径＞30mm或数量＞10|状态栏以外透图（可拍）":{"images":["https://zb-images-1423465873.cos.ap-guangzhou.myqcloud.com/qc-images/1003929100_深圳后验中心仓_图文残影_状态栏以外透图直径＞30mm或数量＞10_状态栏以外透图（可拍）_1780559366684.png"],"note":"机器变换不同角度是可看到有超10的透图"},"1000633018|转转-深圳智能验机中心|前置摄像头|—|拍照坏点":{"images":["https://zb-images-1423465873.cos.ap-guangzhou.myqcloud.com/qc-images/1000633018_转转-深圳智能验机中心_前置摄像头_—_拍照坏点_1780631158192.png"],"note":""},"1006381873|转转-深圳智能验机中心|屏幕|—|外屏-APP黑边红线有缺失":{"images":["https://zb-images-1423465873.cos.ap-guangzhou.myqcloud.com/qc-images/1006381873_转转-深圳智能验机中心_屏幕_—_外屏-APP黑边红线有缺失_1780631183532.png"],"note":""},"1005887117|深圳后验中心仓|机身|—|后壳-样式不匹配":{"images":["https://zb-images-1423465873.cos.ap-guangzhou.myqcloud.com/qc-images/1005887117_深圳后验中心仓_机身_—_后壳-样式不匹配_1780631217190.png"],"note":""},"1004905267|深圳后验中心仓|后置摄像头|—|后摄白底拍照有斑":{"images":["https://zb-images-1423465873.cos.ap-guangzhou.myqcloud.com/qc-images/1004905267_深圳后验中心仓_后置摄像头_—_后摄白底拍照有斑_1780926925564.png"],"note":""},"1004999872|合肥库|机身|—|后壳-与中框有溢胶/撬痕":{"images":["https://zb-images-1423465873.cos.ap-guangzhou.myqcloud.com/qc-images/1004999872_合肥库_机身_—_后壳-与中框有溢胶_撬痕_1780969708084.png"],"note":""},"1005899903|合肥库|屏幕|—|外屏-有胶水溢出/撬痕":{"images":["https://zb-images-1423465873.cos.ap-guangzhou.myqcloud.com/qc-images/1005899903_合肥库_屏幕_—_外屏-有胶水溢出_撬痕_1780969752240.png"],"note":""},"1006760537|合肥库|碎裂/脱胶|—|屏幕边缘脱胶":{"images":["https://zb-images-1423465873.cos.ap-guangzhou.myqcloud.com/qc-images/1006760537_合肥库_碎裂_脱胶_—_屏幕边缘脱胶_1780969829355.png"],"note":""},"1004533734|转转-深圳智能验机中心|碎裂|无|2mm-10mm":{"images":["https://zb-images-1423465873.cos.ap-guangzhou.myqcloud.com/qc-images/1004533734_转转-深圳智能验机中心_碎裂_无_2mm-10mm_1780984953569.png"],"note":""}}